README.md
diapy.py
setup.py
diapy.egg-info/PKG-INFO
diapy.egg-info/SOURCES.txt
diapy.egg-info/dependency_links.txt
diapy.egg-info/requires.txt
diapy.egg-info/top_level.txt