Metadata-Version: 2.1
Name: diapy
Version: 3.1.1
Summary: A minimal diary manager based on python.
Home-page: https://github.com/FiftysixTimes7/diapy
Author: FiftysixTimes7(PTJ)
Author-email: pangtj26@163.com
License: MIT
Keywords: diary
Platform: UNKNOWN
Classifier: License :: OSI Approved :: MIT License
Classifier: Development Status :: 5 - Production/Stable
Classifier: Environment :: Console
Classifier: Natural Language :: English
Classifier: Programming Language :: Python :: 3 :: Only
Classifier: Topic :: Utilities
Requires-Python: >=3.5.0
